[{"segmentIndex":null,"segmentSize":792,"downloadStart":1720856409394,"downloadTime":7},{"segmentIndex":0,"segmentSize":117839,"downloadStart":1720856409406,"downloadTime":89},{"segmentIndex":null,"segmentSize":792,"downloadStart":1720856409502,"downloadTime":7},{"segmentIndex":1,"segmentSize":1920811,"downloadStart":1720856409510,"downloadTime":1353},{"segmentIndex":2,"segmentSize":3469513,"downloadStart":1720856410872,"downloadTime":2443},{"segmentIndex":3,"segmentSize":3350209,"downloadStart":1720856413331,"downloadTime":2053},{"segmentIndex":4,"segmentSize":2074441,"downloadStart":1720856415402,"downloadTime":1334},{"segmentIndex":5,"segmentSize":836620,"downloadStart":1720856416745,"downloadTime":517},{"segmentIndex":6,"segmentSize":3374644,"downloadStart":1720856417267,"downloadTime":2122},{"segmentIndex":7,"segmentSize":3549109,"downloadStart":1720856419402,"downloadTime":2214},{"segmentIndex":8,"segmentSize":3338164,"downloadStart":1720856421647,"downloadTime":2021},{"segmentIndex":9,"segmentSize":1595298,"downloadStart":1720856424102,"downloadTime":977},{"segmentIndex":10,"segmentSize":1325664,"downloadStart":1720856428637,"downloadTime":900},{"segmentIndex":11,"segmentSize":2098020,"downloadStart":1720856433148,"downloadTime":2441},{"segmentIndex":12,"segmentSize":2042462,"downloadStart":1720856437481,"downloadTime":13129},{"segmentIndex":null,"segmentSize":791,"downloadStart":1720856450622,"downloadTime":7},{"segmentIndex":13,"segmentSize":233611,"downloadStart":1720856450630,"downloadTime":284},{"segmentIndex":null,"segmentSize":792,"downloadStart":1720856450917,"downloadTime":4},{"segmentIndex":14,"segmentSize":240769,"downloadStart":1720856450922,"downloadTime":734},{"segmentIndex":null,"segmentSize":792,"downloadStart":1720856451658,"downloadTime":5},{"segmentIndex":15,"segmentSize":893757,"downloadStart":1720856451664,"downloadTime":3115},{"segmentIndex":16,"segmentSize":875854,"downloadStart":1720856455599,"downloadTime":7475},{"segmentIndex":null,"segmentSize":791,"downloadStart":1720856463077,"downloadTime":7},{"segmentIndex":17,"segmentSize":334497,"downloadStart":1720856463084,"downloadTime":1041},{"segmentIndex":18,"segmentSize":451132,"downloadStart":1720856464684,"downloadTime":7424},{"segmentIndex":null,"segmentSize":792,"downloadStart":1720856472111,"downloadTime":8},{"segmentIndex":19,"segmentSize":258731,"downloadStart":1720856472120,"downloadTime":1178},{"segmentIndex":20,"segmentSize":284830,"downloadStart":1720856473402,"downloadTime":3881},{"segmentIndex":21,"segmentSize":272484,"downloadStart":1720856477990,"downloadTime":4379},{"segmentIndex":22,"segmentSize":231100,"downloadStart":1720856482471,"downloadTime":3753},{"segmentIndex":23,"segmentSize":457049,"downloadStart":1720856487040,"downloadTime":5393},{"segmentIndex":24,"segmentSize":459699,"downloadStart":1720856492437,"downloadTime":6337},{"segmentIndex":25,"segmentSize":333726,"downloadStart":1720856498777,"downloadTime":2117},{"segmentIndex":26,"segmentSize":486831,"downloadStart":1720856500896,"downloadTime":8959},{"segmentIndex":null,"segmentSize":791,"downloadStart":1720856509859,"downloadTime":8},{"segmentIndex":27,"segmentSize":188491,"downloadStart":1720856509868,"downloadTime":1758},{"segmentIndex":28,"segmentSize":123017,"downloadStart":1720856511628,"downloadTime":10784},{"segmentIndex":null,"segmentSize":791,"downloadStart":1720856522415,"downloadTime":5},{"segmentIndex":29,"segmentSize":210964,"downloadStart":1720856522421,"downloadTime":1647},{"segmentIndex":30,"segmentSize":192494,"downloadStart":1720856524070,"downloadTime":3243},{"segmentIndex":null,"segmentSize":792,"downloadStart":1720856527316,"downloadTime":4},{"segmentIndex":31,"segmentSize":416438,"downloadStart":1720856527321,"downloadTime":377},{"segmentIndex":32,"segmentSize":494619,"downloadStart":1720856527701,"downloadTime":3429},{"segmentIndex":null,"segmentSize":791,"downloadStart":1720856532074,"downloadTime":6},{"segmentIndex":33,"segmentSize":232820,"downloadStart":1720856532081,"downloadTime":3382},{"segmentIndex":34,"segmentSize":287925,"downloadStart":1720856536716,"downloadTime":4909},{"segmentIndex":35,"segmentSize":240359,"downloadStart":1720856541626,"downloadTime":3954},{"segmentIndex":36,"segmentSize":213181,"downloadStart":1720856545582,"downloadTime":8928},{"segmentIndex":null,"segmentSize":791,"downloadStart":1720856554512,"downloadTime":10},{"segmentIndex":37,"segmentSize":144348,"downloadStart":1720856554523,"downloadTime":2277},{"segmentIndex":38,"segmentSize":111744,"downloadStart":1720856556801,"downloadTime":12601},{"segmentIndex":39,"segmentSize":65304,"downloadStart":1720856569404,"downloadTime":7770},{"segmentIndex":40,"segmentSize":162955,"downloadStart":1720856577178,"downloadTime":14716},{"segmentIndex":41,"segmentSize":186133,"downloadStart":1720856591895,"downloadTime":4859},{"segmentIndex":42,"segmentSize":195246,"downloadStart":1720856596756,"downloadTime":2826},{"segmentIndex":43,"segmentSize":126620,"downloadStart":1720856599584,"downloadTime":2897},{"segmentIndex":44,"segmentSize":151514,"downloadStart":1720856602483,"downloadTime":13266},{"segmentIndex":45,"segmentSize":105093,"downloadStart":1720856615751,"downloadTime":4382},{"segmentIndex":46,"segmentSize":105580,"downloadStart":1720856620134,"downloadTime":1215},{"segmentIndex":47,"segmentSize":203026,"downloadStart":1720856621350,"downloadTime":1780},{"segmentIndex":48,"segmentSize":211019,"downloadStart":1720856623131,"downloadTime":1214},{"segmentIndex":49,"segmentSize":110415,"downloadStart":1720856624346,"downloadTime":691},{"segmentIndex":50,"segmentSize":95614,"downloadStart":1720856625039,"downloadTime":970},{"segmentIndex":null,"segmentSize":791,"downloadStart":1720856626011,"downloadTime":5},{"segmentIndex":51,"segmentSize":308907,"downloadStart":1720856626016,"downloadTime":1591},{"segmentIndex":52,"segmentSize":229420,"downloadStart":1720856627610,"downloadTime":3285},{"segmentIndex":53,"segmentSize":103859,"downloadStart":1720856630897,"downloadTime":4088},{"segmentIndex":54,"segmentSize":250527,"downloadStart":1720856634986,"downloadTime":8043},{"segmentIndex":55,"segmentSize":454087,"downloadStart":1720856643031,"downloadTime":4082},{"segmentIndex":56,"segmentSize":270140,"downloadStart":1720856647115,"downloadTime":2109},{"segmentIndex":57,"segmentSize":277368,"downloadStart":1720856649226,"downloadTime":4460},{"segmentIndex":58,"segmentSize":324206,"downloadStart":1720856653688,"downloadTime":4736},{"segmentIndex":null,"segmentSize":792,"downloadStart":1720856658428,"downloadTime":5},{"segmentIndex":59,"segmentSize":475593,"downloadStart":1720856658433,"downloadTime":2087},{"segmentIndex":60,"segmentSize":375333,"downloadStart":1720856660524,"downloadTime":2381},{"segmentIndex":61,"segmentSize":817634,"downloadStart":1720856662907,"downloadTime":9418},{"segmentIndex":null,"segmentSize":791,"downloadStart":1720856672329,"downloadTime":8},{"segmentIndex":62,"segmentSize":185355,"downloadStart":1720856672338,"downloadTime":562},{"segmentIndex":63,"segmentSize":155017,"downloadStart":1720856672901,"downloadTime":2236},{"segmentIndex":64,"segmentSize":81223,"downloadStart":1720856676058,"downloadTime":3403},{"segmentIndex":null,"segmentSize":792,"downloadStart":1720856680619,"downloadTime":6},{"segmentIndex":65,"segmentSize":321045,"downloadStart":1720856680625,"downloadTime":4371},{"segmentIndex":66,"segmentSize":535094,"downloadStart":1720856684998,"downloadTime":5248},{"segmentIndex":67,"segmentSize":512184,"downloadStart":1720856690249,"downloadTime":3857},{"segmentIndex":null,"segmentSize":791,"downloadStart":1720856694109,"downloadTime":5},{"segmentIndex":68,"segmentSize":381313,"downloadStart":1720856694115,"downloadTime":4224},{"segmentIndex":69,"segmentSize":323853,"downloadStart":1720856698341,"downloadTime":4185},{"segmentIndex":70,"segmentSize":419136,"downloadStart":1720856702944,"downloadTime":5602},{"segmentIndex":71,"segmentSize":346883,"downloadStart":1720856708548,"downloadTime":3620},{"segmentIndex":72,"segmentSize":392166,"downloadStart":1720856712170,"downloadTime":9161},{"segmentIndex":73,"segmentSize":386164,"downloadStart":1720856721333,"downloadTime":5204},{"segmentIndex":74,"segmentSize":281111,"downloadStart":1720856726540,"downloadTime":3892},{"segmentIndex":75,"segmentSize":276625,"downloadStart":1720856730434,"downloadTime":4027},{"segmentIndex":76,"segmentSize":181101,"downloadStart":1720856734463,"downloadTime":1193},{"segmentIndex":null,"segmentSize":792,"downloadStart":1720856735658,"downloadTime":5},{"segmentIndex":77,"segmentSize":840254,"downloadStart":1720856735664,"downloadTime":10864},{"segmentIndex":null,"segmentSize":791,"downloadStart":1720856746532,"downloadTime":9},{"segmentIndex":78,"segmentSize":393825,"downloadStart":1720856746543,"downloadTime":3500},{"segmentIndex":79,"segmentSize":407119,"downloadStart":1720856750045,"downloadTime":3889},{"segmentIndex":80,"segmentSize":465350,"downloadStart":1720856753936,"downloadTime":11881},{"segmentIndex":null,"segmentSize":791,"downloadStart":1720856765819,"downloadTime":10},{"segmentIndex":81,"segmentSize":140688,"downloadStart":1720856765830,"downloadTime":1124},{"segmentIndex":82,"segmentSize":195489,"downloadStart":1720856766955,"downloadTime":1823},{"segmentIndex":null,"segmentSize":791,"downloadStart":1720856768780,"downloadTime":4},{"segmentIndex":83,"segmentSize":286038,"downloadStart":1720856768785,"downloadTime":3033},{"segmentIndex":84,"segmentSize":172322,"downloadStart":1720856771820,"downloadTime":3405},{"segmentIndex":85,"segmentSize":233972,"downloadStart":1720856775227,"downloadTime":4047},{"segmentIndex":86,"segmentSize":86660,"downloadStart":1720856779276,"downloadTime":4229},{"segmentIndex":null,"segmentSize":791,"downloadStart":1720856783507,"downloadTime":4},{"segmentIndex":87,"segmentSize":83101,"downloadStart":1720856783512,"downloadTime":4651},{"segmentIndex":88,"segmentSize":120482,"downloadStart":1720856788164,"downloadTime":4211},{"segmentIndex":89,"segmentSize":130091,"downloadStart":1720856792376,"downloadTime":4099},{"segmentIndex":90,"segmentSize":146399,"downloadStart":1720856796477,"downloadTime":5096},{"segmentIndex":91,"segmentSize":113930,"downloadStart":1720856801575,"downloadTime":499},{"segmentIndex":92,"segmentSize":158791,"downloadStart":1720856802076,"downloadTime":3714},{"segmentIndex":93,"segmentSize":151983,"downloadStart":1720856806610,"downloadTime":3339},{"segmentIndex":94,"segmentSize":357737,"downloadStart":1720856811183,"downloadTime":4754},{"segmentIndex":95,"segmentSize":276143,"downloadStart":1720856815939,"downloadTime":3650},{"segmentIndex":null,"segmentSize":792,"downloadStart":1720856819939,"downloadTime":6},{"segmentIndex":96,"segmentSize":888160,"downloadStart":1720856819946,"downloadTime":7144},{"segmentIndex":97,"segmentSize":1148496,"downloadStart":1720856827094,"downloadTime":9253},{"segmentIndex":98,"segmentSize":388024,"downloadStart":1720856836353,"downloadTime":2751},{"segmentIndex":99,"segmentSize":1370198,"downloadStart":1720856839106,"downloadTime":16623},{"segmentIndex":null,"segmentSize":791,"downloadStart":1720856855737,"downloadTime":8},{"segmentIndex":100,"segmentSize":144906,"downloadStart":1720856855745,"downloadTime":474},{"segmentIndex":101,"segmentSize":294290,"downloadStart":1720856856220,"downloadTime":2516},{"segmentIndex":102,"segmentSize":200798,"downloadStart":1720856858738,"downloadTime":1321},{"segmentIndex":103,"segmentSize":217359,"downloadStart":1720856860061,"downloadTime":1264},{"segmentIndex":104,"segmentSize":377292,"downloadStart":1720856861327,"downloadTime":4898},{"segmentIndex":null,"segmentSize":792,"downloadStart":1720856866227,"downloadTime":5},{"segmentIndex":105,"segmentSize":483863,"downloadStart":1720856866232,"downloadTime":3514},{"segmentIndex":null,"segmentSize":791,"downloadStart":1720856869749,"downloadTime":8},{"segmentIndex":106,"segmentSize":219145,"downloadStart":1720856869758,"downloadTime":1150},{"segmentIndex":107,"segmentSize":173320,"downloadStart":1720856870909,"downloadTime":3387},{"segmentIndex":108,"segmentSize":104617,"downloadStart":1720856874298,"downloadTime":3631},{"segmentIndex":109,"segmentSize":177514,"downloadStart":1720856878534,"downloadTime":4009},{"segmentIndex":110,"segmentSize":108981,"downloadStart":1720856883152,"downloadTime":3399},{"segmentIndex":111,"segmentSize":110385,"downloadStart":1720856887383,"downloadTime":3893},{"segmentIndex":112,"segmentSize":174470,"downloadStart":1720856891921,"downloadTime":4620},{"segmentIndex":113,"segmentSize":196826,"downloadStart":1720856896542,"downloadTime":3788},{"segmentIndex":114,"segmentSize":219006,"downloadStart":1720856901034,"downloadTime":4292},{"segmentIndex":null,"segmentSize":792,"downloadStart":1720856905430,"downloadTime":5},{"segmentIndex":115,"segmentSize":462794,"downloadStart":1720856905436,"downloadTime":6749},{"segmentIndex":null,"segmentSize":791,"downloadStart":1720856912188,"downloadTime":8},{"segmentIndex":116,"segmentSize":197335,"downloadStart":1720856912197,"downloadTime":6031},{"segmentIndex":117,"segmentSize":224437,"downloadStart":1720856918230,"downloadTime":992},{"segmentIndex":118,"segmentSize":193701,"downloadStart":1720856919223,"downloadTime":3283},{"segmentIndex":119,"segmentSize":235583,"downloadStart":1720856923646,"downloadTime":4857},{"segmentIndex":120,"segmentSize":297543,"downloadStart":1720856928505,"downloadTime":4350},{"segmentIndex":121,"segmentSize":294869,"downloadStart":1720856932857,"downloadTime":5646},{"segmentIndex":122,"segmentSize":288033,"downloadStart":1720856938505,"downloadTime":7684},{"segmentIndex":123,"segmentSize":350572,"downloadStart":1720856946191,"downloadTime":2140},{"segmentIndex":124,"segmentSize":458057,"downloadStart":1720856948333,"downloadTime":7864},{"segmentIndex":125,"segmentSize":309233,"downloadStart":1720856956199,"downloadTime":7693},{"segmentIndex":126,"segmentSize":230343,"downloadStart":1720856963896,"downloadTime":3844},{"segmentIndex":127,"segmentSize":152400,"downloadStart":1720856967742,"downloadTime":2354},{"segmentIndex":128,"segmentSize":226986,"downloadStart":1720856970097,"downloadTime":6507},{"segmentIndex":129,"segmentSize":318632,"downloadStart":1720856976606,"downloadTime":5009},{"segmentIndex":130,"segmentSize":335011,"downloadStart":1720856981617,"downloadTime":5582},{"segmentIndex":131,"segmentSize":366673,"downloadStart":1720856987201,"downloadTime":7439},{"segmentIndex":null,"segmentSize":791,"downloadStart":1720856994643,"downloadTime":8},{"segmentIndex":132,"segmentSize":200660,"downloadStart":1720856994652,"downloadTime":4098},{"segmentIndex":133,"segmentSize":189823,"downloadStart":1720856998751,"downloadTime":4029},{"segmentIndex":134,"segmentSize":121338,"downloadStart":1720857002782,"downloadTime":3438},{"segmentIndex":135,"segmentSize":48473,"downloadStart":1720857006222,"downloadTime":2835},{"segmentIndex":136,"segmentSize":24278,"downloadStart":1720857009058,"downloadTime":3707},{"segmentIndex":137,"segmentSize":44051,"downloadStart":1720857012766,"downloadTime":4613},{"segmentIndex":138,"segmentSize":51297,"downloadStart":1720857017381,"downloadTime":4537},{"segmentIndex":139,"segmentSize":68490,"downloadStart":1720857021919,"downloadTime":4778},{"segmentIndex":140,"segmentSize":87113,"downloadStart":1720857026698,"downloadTime":4623}]